Metadata-Version: 2.1
Name: oneNeuron-pypi-atishay2411
Version: 0.0.1
Summary: It is an implementation of Perceptron
Home-page: https://github.com/atishay2411/oneNeuron_pypi
Author: Atishay Jain
Author-email: jain.atishay2411@gmail.com
License: UNKNOWN
Project-URL: Bug Tracker, https://github.com/atishay2411/oneNeuron_pypi/issues
Platform: UNKNOWN
Classifier: Programming Language :: Python :: 3
Classifier: License :: OSI Approved :: MIT License
Classifier: Operating System :: OS Independent
Requires-Python: >=3.6
License-File: LICENSE
Requires-Dist: numpy
Requires-Dist: tqdm
